{"total":1,"count":1,"start":0,"items":[{"ID":"2OZcvc6puZWsglavGuRVcyuNDhSGwFvDAn6tKMhWprQ=@mailhog.example","From":{"Relays":null,"Mailbox":"ayoubbarahal2","Domain":"gmail.com","Params":""},"To":[{"Relays":null,"Mailbox":"ayoubbarahal2","Domain":"gmail.com","Params":""}],"Content":{"Headers":{"Content-Transfer-Encoding":["8Bit"],"Content-Type":["text/html; charset=utf-8"],"Date":["Mon, 23 Mar 2026 13:27:35 +0100"],"From":["ScheduleHub \u003ctest@schedulehub.local\u003e"],"MIME-Version":["1.0"],"Message-ID":["\u003cS7KNBmIex2tFrMBYEfieDjxJRd4fBmQwYI0vYtG1dsw@default\u003e"],"Received":["from default by mailhog.example (MailHog)\r\n          id 2OZcvc6puZWsglavGuRVcyuNDhSGwFvDAn6tKMhWprQ=@mailhog.example; Mon, 23 Mar 2026 12:27:35 +0000"],"Return-Path":["\u003cayoubbarahal2@gmail.com\u003e"],"Subject":["=?utf-8?Q?Rendez-vous_confirm=C3=A9_-_schedule_hub?="],"To":["ayoubbarahal2@gmail.com"],"X-Mailer":["PHPMailer 6.12.0 (https://github.com/PHPMailer/PHPMailer)"]},"Body":"\u003cdiv style=\"font-family: Arial, sans-serif; max-width: 600px; margin: 0 auto; padding: 20px;\"\u003e\r\n  \u003cdiv style=\"background: #0074bd; color: #fff; padding: 20px; border-radius: 6px 6px 0 0; text-align: center;\"\u003e\r\n    \u003ch1 style=\"margin: 0; font-size: 22px;\"\u003e\u0026#10003; Rendez-vous confirmé\u003c/h1\u003e\r\n  \u003c/div\u003e\r\n\r\n  \u003cdiv style=\"border: 1px solid #ddd; border-top: none; padding: 20px; border-radius: 0 0 6px 6px;\"\u003e\r\n    \u003cp\u003eBonjour \u003cstrong\u003eAyoub Barahal\u003c/strong\u003e,\u003c/p\u003e\r\n\r\n    \u003cp\u003eVotre rendez-vous a été confirmé avec les détails suivants :\u003c/p\u003e\r\n\r\n    \u003ctable style=\"width: 100%; border-collapse: collapse; margin: 15px 0;\"\u003e\r\n      \u003ctr\u003e\r\n        \u003ctd style=\"padding: 8px; border-bottom: 1px solid #eee; color: #666; width: 40%;\"\u003eRéférence\u003c/td\u003e\r\n        \u003ctd style=\"padding: 8px; border-bottom: 1px solid #eee;\"\u003e\u003cstrong\u003e#8\u003c/strong\u003e\u003c/td\u003e\r\n      \u003c/tr\u003e\r\n      \u003ctr\u003e\r\n        \u003ctd style=\"padding: 8px; border-bottom: 1px solid #eee; color: #666;\"\u003eAgence\u003c/td\u003e\r\n        \u003ctd style=\"padding: 8px; border-bottom: 1px solid #eee;\"\u003eNorth Branch\u003c/td\u003e\r\n      \u003c/tr\u003e\r\n      \u003ctr\u003e\r\n        \u003ctd style=\"padding: 8px; border-bottom: 1px solid #eee; color: #666;\"\u003eConseiller\u003c/td\u003e\r\n        \u003ctd style=\"padding: 8px; border-bottom: 1px solid #eee;\"\u003eLeo Grant\u003c/td\u003e\r\n      \u003c/tr\u003e\r\n      \u003ctr\u003e\r\n        \u003ctd style=\"padding: 8px; border-bottom: 1px solid #eee; color: #666;\"\u003eType de rendez-vous\u003c/td\u003e\r\n        \u003ctd style=\"padding: 8px; border-bottom: 1px solid #eee;\"\u003eFollow-up\u003c/td\u003e\r\n      \u003c/tr\u003e\r\n      \u003ctr\u003e\r\n        \u003ctd style=\"padding: 8px; border-bottom: 1px solid #eee; color: #666;\"\u003eDate et heure\u003c/td\u003e\r\n        \u003ctd style=\"padding: 8px; border-bottom: 1px solid #eee;\"\u003e\u003cstrong\u003e24/03/2026 à 14:00\u003c/strong\u003e\u003c/td\u003e\r\n      \u003c/tr\u003e\r\n    \u003c/table\u003e\r\n\r\n        \u003cp style=\"text-align: center; margin: 25px 0;\"\u003e\r\n      \u003ca href=\"/appointment/8/confirmation\" style=\"background: #0074bd; color: #fff; padding: 12px 30px; text-decoration: none; border-radius: 4px; display: inline-block;\"\u003e\r\n        Gérer mon rendez-vous\r\n      \u003c/a\u003e\r\n    \u003c/p\u003e\r\n    \r\n    \u003cp style=\"color: #999; font-size: 12px; margin-top: 20px; border-top: 1px solid #eee; padding-top: 15px;\"\u003e\r\n      Ce message a été envoyé automatiquement par schedule hub.\r\n      N'hésitez pas à nous contacter si vous avez des questions.\r\n    \u003c/p\u003e\r\n  \u003c/div\u003e\r\n\u003c/div\u003e\r\n","Size":2669,"MIME":null},"Created":"2026-03-23T12:27:35.835089144Z","MIME":null,"Raw":{"From":"ayoubbarahal2@gmail.com","To":["ayoubbarahal2@gmail.com"],"Data":"Date: Mon, 23 Mar 2026 13:27:35 +0100\r\nTo: ayoubbarahal2@gmail.com\r\nFrom: ScheduleHub \u003ctest@schedulehub.local\u003e\r\nSubject: =?utf-8?Q?Rendez-vous_confirm=C3=A9_-_schedule_hub?=\r\nMessage-ID: \u003cS7KNBmIex2tFrMBYEfieDjxJRd4fBmQwYI0vYtG1dsw@default\u003e\r\nX-Mailer: PHPMailer 6.12.0 (https://github.com/PHPMailer/PHPMailer)\r\nMIME-Version: 1.0\r\nContent-Type: text/html; charset=utf-8\r\nContent-Transfer-Encoding: 8Bit\r\n\r\n\u003cdiv style=\"font-family: Arial, sans-serif; max-width: 600px; margin: 0 auto; padding: 20px;\"\u003e\r\n  \u003cdiv style=\"background: #0074bd; color: #fff; padding: 20px; border-radius: 6px 6px 0 0; text-align: center;\"\u003e\r\n    \u003ch1 style=\"margin: 0; font-size: 22px;\"\u003e\u0026#10003; Rendez-vous confirmé\u003c/h1\u003e\r\n  \u003c/div\u003e\r\n\r\n  \u003cdiv style=\"border: 1px solid #ddd; border-top: none; padding: 20px; border-radius: 0 0 6px 6px;\"\u003e\r\n    \u003cp\u003eBonjour \u003cstrong\u003eAyoub Barahal\u003c/strong\u003e,\u003c/p\u003e\r\n\r\n    \u003cp\u003eVotre rendez-vous a été confirmé avec les détails suivants :\u003c/p\u003e\r\n\r\n    \u003ctable style=\"width: 100%; border-collapse: collapse; margin: 15px 0;\"\u003e\r\n      \u003ctr\u003e\r\n        \u003ctd style=\"padding: 8px; border-bottom: 1px solid #eee; color: #666; width: 40%;\"\u003eRéférence\u003c/td\u003e\r\n        \u003ctd style=\"padding: 8px; border-bottom: 1px solid #eee;\"\u003e\u003cstrong\u003e#8\u003c/strong\u003e\u003c/td\u003e\r\n      \u003c/tr\u003e\r\n      \u003ctr\u003e\r\n        \u003ctd style=\"padding: 8px; border-bottom: 1px solid #eee; color: #666;\"\u003eAgence\u003c/td\u003e\r\n        \u003ctd style=\"padding: 8px; border-bottom: 1px solid #eee;\"\u003eNorth Branch\u003c/td\u003e\r\n      \u003c/tr\u003e\r\n      \u003ctr\u003e\r\n        \u003ctd style=\"padding: 8px; border-bottom: 1px solid #eee; color: #666;\"\u003eConseiller\u003c/td\u003e\r\n        \u003ctd style=\"padding: 8px; border-bottom: 1px solid #eee;\"\u003eLeo Grant\u003c/td\u003e\r\n      \u003c/tr\u003e\r\n      \u003ctr\u003e\r\n        \u003ctd style=\"padding: 8px; border-bottom: 1px solid #eee; color: #666;\"\u003eType de rendez-vous\u003c/td\u003e\r\n        \u003ctd style=\"padding: 8px; border-bottom: 1px solid #eee;\"\u003eFollow-up\u003c/td\u003e\r\n      \u003c/tr\u003e\r\n      \u003ctr\u003e\r\n        \u003ctd style=\"padding: 8px; border-bottom: 1px solid #eee; color: #666;\"\u003eDate et heure\u003c/td\u003e\r\n        \u003ctd style=\"padding: 8px; border-bottom: 1px solid #eee;\"\u003e\u003cstrong\u003e24/03/2026 à 14:00\u003c/strong\u003e\u003c/td\u003e\r\n      \u003c/tr\u003e\r\n    \u003c/table\u003e\r\n\r\n        \u003cp style=\"text-align: center; margin: 25px 0;\"\u003e\r\n      \u003ca href=\"/appointment/8/confirmation\" style=\"background: #0074bd; color: #fff; padding: 12px 30px; text-decoration: none; border-radius: 4px; display: inline-block;\"\u003e\r\n        Gérer mon rendez-vous\r\n      \u003c/a\u003e\r\n    \u003c/p\u003e\r\n    \r\n    \u003cp style=\"color: #999; font-size: 12px; margin-top: 20px; border-top: 1px solid #eee; padding-top: 15px;\"\u003e\r\n      Ce message a été envoyé automatiquement par schedule hub.\r\n      N'hésitez pas à nous contacter si vous avez des questions.\r\n    \u003c/p\u003e\r\n  \u003c/div\u003e\r\n\u003c/div\u003e\r\n","Helo":"default"}}]}